pokemon_haru/__init__.py
pokemon_haru/pokemon.csv
pokemon_haru/random_pokemon.py
pokemon_haru-1.0.1.dist-info/METADATA
pokemon_haru-1.0.1.dist-info/WHEEL
pokemon_haru-1.0.1.dist-info/top_level.txt
pokemon_haru-1.0.1.dist-info/RECORD
